vsutillib/network/__init__.py
vsutillib/network/network.py
vsutillib/network/classes/__init__.py
vsutillib/network/classes/urlrequest.py
vsutillib_network-1.6.0.dist-info/AUTHORS
vsutillib_network-1.6.0.dist-info/LICENSE.txt
vsutillib_network-1.6.0.dist-info/METADATA
vsutillib_network-1.6.0.dist-info/WHEEL
vsutillib_network-1.6.0.dist-info/top_level.txt
vsutillib_network-1.6.0.dist-info/RECORD
