Metadata-Version: 2.1
Name: vsutillib-network
Version: 1.6.0
Summary: vsutillib.network sub package part of vsutillib
Home-page: https://pypi.org/project/vsutillib-network/
Author: Efrain Vergara
Author-email: akai10tsuki@gmail.com
License: MIT
Platform: UNKNOWN
Requires-Python: >=3.8.1, <3.9
